qamlzim/__init__.py
qamlzim/anneal.py
qamlzim/anneal_basic.py
qamlzim/anneal_copy.py
qamlzim/anneal_functions.py
qamlzim/anneal_qac.py
qamlzim/model.py
qamlzim/prune_functions.py
qamlzim/train_env.py
qamlzim-1.0.0.dist-info/LICENSE
qamlzim-1.0.0.dist-info/METADATA
qamlzim-1.0.0.dist-info/WHEEL
qamlzim-1.0.0.dist-info/top_level.txt
qamlzim-1.0.0.dist-info/RECORD
