Metadata-Version: 2.1
Name: qamlzim
Version: 1.0.0
Summary: Binary Classifier trained with D-Wave's Quantum Annealers.
Home-page: https://github.com/tcoulvert/qamlzim
Author: Thomas Sievert
Author-email: 63161166+tcoulvert@users.noreply.github.com
Classifier: Programming Language :: Python :: 3
Classifier: License :: OSI Approved :: MIT License
Classifier: Operating System :: OS Independent
License-File: LICENSE
Requires-Dist: numpy (>=1.20.3)
Requires-Dist: scikit-learn (>=1.0.1)
Requires-Dist: scipy (>=1.7.1)
Requires-Dist: dwave-ocean-sdk (>=4.2.0)
Provides-Extra: dev
Requires-Dist: pytest (>=3.7) ; extra == 'dev'
Requires-Dist: check-manifest (>=0.47) ; extra == 'dev'
